.gitignore
CHANGES.md
README.md
setup.py
server_reloader/__init__.py
server_reloader.egg-info/PKG-INFO
server_reloader.egg-info/SOURCES.txt
server_reloader.egg-info/dependency_links.txt
server_reloader.egg-info/top_level.txt