Metadata-Version: 1.0
Name: server-reloader
Version: 0.1.3
Summary: Provides easy way to reload you server on code changes or another events
Home-page: http://github.com/svetlyak40wt/server-reloader/
Author: Alexander Artemenko
Author-email: svetlyak.40wt@gmail.com
License: New BSD License
Keywords: server code reload reloader restarter
Platform: UNKNOWN
Classifier: Development Status :: 4 - Beta
Classifier: Intended Audience :: Developers
Classifier: License :: OSI Approved :: BSD License
Classifier: Programming Language :: Python
Classifier: Topic :: Software Development :: Libraries :: Python Modules
